{"ticker": "AMAG", "name": "PT Asuransi Multi Artha Guna Tbk", "sector": "Financial Services", "industry": "Insurance - Property & Casualty", "website": "https://www.mag.co.id", "summary": "PT Asuransi Multi Artha Guna Tbk provides general insurance in Indonesia. It operates through Motor Vehicles, Health, Fire, and Other segments. The company offers MAGNA car protection that covers loss or damage to the car, which includes the value of the vehicle or its equipment; MAGNA Sehat, which provides healthcare coverage and hospitalization; MAGNA Properti that covers loss or damage to the i", "currency": "IDR", "updated": "2026-06-07 00:51", "last_price": 382.0, "prev_close": 384.0, "week52_high": 510.0, "week52_low": 340.0, "week52_change_pct": 4.89, "beta": -0.09, "avg_volume": 134660, "shares": 4945746416, "float_shares": 557999732, "float_pct": 11.28, "pe": 9.754852, "pe_annualised": 9.754852, "forward_pe": null, "earn_yield": 10.25, "pb": 0.8618356, "ps": 0.62966913, "price_cf": 43.61, "price_fcf": 48.82, "ev_ebit": 5.331, "ev_ebitda": 5.331, "ev_revenue": 0.379, "peg": null, "eps": 39.16, "eps_fwd": null, "bv": 443.24, "rev_ps": 478.0, "cash_ps": 98.61, "fcf_ps": 7.83, "current_ratio": 1.402, "quick_ratio": 0.329, "der": null, "der_q": null, "lt_der_q": null, "tl_eq_q": 1.6471, "td_ta_q": null, "lev_q": 2.6471, "gpm": 0.18323, "opm": 0.09126, "npm": 0.06458, "ebitda_margin": 0.07101, "roe": 0.09522, "roa": 0.02125, "rev_yoy": -21.27, "ni_yoy": 109.79, "gp_yoy": null, "dividend": 30.0, "dividend_ttm": 30.0, "dividend_yield": 7.85, "payout_ratio": 1.0217, "ex_dividend_date": "07 May 26", "div_history": [{"year": "2026", "ex_date": "07 May 26", "amount": 30.0}, {"year": "2025", "ex_date": "14 May 25", "amount": 40.0}, {"year": "2024", "ex_date": "07 May 24", "amount": 30.0}, {"year": "2023", "ex_date": "06 Jul 23", "amount": 20.0}, {"year": "2022", "ex_date": "08 Jul 22", "amount": 50.0}, {"year": "2021", "ex_date": "07 Jul 21", "amount": 50.0}], "ttm_revenue": 2364043781000.0, "ttm_gross": 549775081472, "ttm_ebitda": 213058256896, "ttm_net_income": 175112501000.0, "ttm_op_income": null, "lq_cash": 487704560000.0, "lq_assets": 5804603143000.0, "lq_tot_liab": 3611786057000.0, "lq_wc": null, "lq_equity": 2192817086000.0, "lq_lt_debt": null, "lq_st_debt": null, "lq_total_debt": null, "lq_net_debt": null, "ttm_ocf": 43319881728, "ttm_icf": -29580819000.0, "ttm_fincf": -199801419000.0, "ttm_capex": null, "ttm_fcf": 38701437000.0, "market_cap": 1889275084800, "enterprise_value": 1135712665600, "q_revenue": {"2026": {"Q1": 433641577000.0}, "2025": {"Q4": 607187915000.0, "Q3": 696304396000.0, "Q2": 626909893000.0, "Q1": 550799514000.0}}, "q_net_income": {"2026": {"Q1": 71234788000.0}, "2025": {"Q4": 41360943000.0, "Q3": 42321055000.0, "Q2": 20195715000.0, "Q1": 33956019000.0}}, "q_eps": {"2026": {"Q1": 14.4}, "2025": {"Q4": 8.36, "Q3": 8.56, "Q2": 4.08, "Q1": 6.87}}, "q_gross": {}, "q_op_income": {}, "q_assets": {"2026": {"Q1": 5804603143000.0}, "2025": {"Q4": 5748462058000.0, "Q3": 5426749267000.0, "Q2": 5141740678000.0, "Q1": 6124469850000.0}}, "q_equity": {"2026": {"Q1": 2192817086000.0}, "2025": {"Q4": 2167537463000.0, "Q3": 1970402738000.0, "Q2": 1796751609000.0, "Q1": 1877063283000.0}}, "q_debt": {}, "q_cash": {"2026": {"Q1": 487704560000.0}, "2025": {"Q4": 485425155000.0, "Q3": 593181485000.0, "Q2": 505400466000.0, "Q1": 657503798000.0}}, "q_ocf": {"2025": {"Q3": 19164005000.0}}, "q_fcf": {"2026": {"Q1": 67981982000.0}, "2025": {"Q4": 12052948000.0, "Q3": 17479998000.0, "Q2": -58813491000.0, "Q1": 121184774000.0}}, "a_revenue": {"2025": 2258414424000.0, "2024": 2062802109000.0, "2023": 1095347174000.0, "2022": 1025174188000.0}, "a_net_income": {"2025": 156487381000.0, "2024": 265241035000.0, "2023": 148073877000.0, "2022": 169774422000.0}, "hist_revenue": {"2025": 2258414424000.0, "2024": 2062802109000.0, "2023": 1095347174000.0, "2022": 1025174188000.0}, "hist_gross_profit": {}, "hist_operating_income": {}, "hist_net_income": {"2025": 156487381000.0, "2024": 265241035000.0, "2023": 148073877000.0, "2022": 169774422000.0}, "hist_total_assets": {"2025": 5748462058000.0, "2024": 5142908657000.0, "2023": 4909833143000.0, "2022": 4717862245000.0}, "hist_total_equity": {"2025": 2167537463000.0, "2024": 1980119437000.0, "2023": 1836496209000.0, "2022": 1700336893000.0}, "hist_total_debt": {}, "price_perf": {}, "hist_eps": {"2025": 31.64, "2024": 53.63, "2023": 29.94, "2022": 34.33}, "hist_fcf": {"2022": 226403808000.0, "2025": 91904229000.0, "2023": 139162725000.0, "2024": 78246073000.0}, "hist_bv": {"2025": 438.26, "2024": 400.37, "2023": 371.33, "2022": 343.8}, "hist_roe": {"2022": 9.98, "2025": 7.22, "2023": 8.06, "2024": 13.4}, "hist_dps": {"2011": 10.0, "2012": 10.0, "2013": 12.0, "2014": 12.0, "2015": 10.0, "2017": 8.0, "2020": 30.0, "2021": 50.0, "2022": 50.0, "2023": 20.0, "2024": 30.0, "2025": 40.0, "2026": 30.0}, "eps_cagr_3y": 2.8, "eps_cagr_2y": -41.0, "ddm_g_rate": 0.0, "div_years": 13, "sector_pe_median": 11.4428, "sector_pb_median": 0.7989, "sector_npm_median": 0.132, "sector_roe_median": 0.0509, "sector_ev_ebitda_median": 5.782, "sector_stock_count": 103, "pe_vs_sector_pct": -14.8, "pb_vs_sector_pct": 7.9}