{"ticker":"CCSI","name":"PT Communication Cable Systems Indonesia Tbk","sector":"Technology","industry":"Communication Equipment","website":"https://www.ccsi.co.id","summary":"PT Communication Cable Systems Indonesia Tbk manufactures and sells telecommunications fiber optic cables in Indonesia and internationally. The company offers fiber optic cables, such as submarine, outdoor, indoor, and special capable cables. It also provides high density polyethylene pipes comprising subduct, macroduct/microduct, gas, and water pipes; and reinforced thermoplastic pipes. In additi","currency":"IDR","updated":"2026-06-07 13:08","last_price":230.0,"prev_close":230.0,"week52_high":450.0,"week52_low":210.0,"week52_change_pct":-28.65,"beta":0.21,"avg_volume":682377,"shares":1333333331,"float_shares":373119999,"float_pct":27.98,"pe":7.073876,"pe_annualised":7.073876,"forward_pe":null,"earn_yield":14.14,"pb":0.55666757,"ps":0.9839123,"price_cf":-28.5,"price_fcf":-8.7,"ev_ebit":10.056,"ev_ebitda":10.056,"ev_revenue":1.171,"peg":null,"eps":32.514,"eps_fwd":null,"bv":413.173,"rev_ps":233.76,"cash_ps":null,"fcf_ps":-26.44,"current_ratio":2.753,"quick_ratio":0.728,"der":16.166,"der_q":null,"lt_der_q":null,"tl_eq_q":null,"td_ta_q":null,"lev_q":null,"gpm":0.17523001,"opm":0.041050002,"npm":0.02671,"ebitda_margin":0.116409995,"roe":0.01381,"roa":0.01485,"rev_yoy":null,"ni_yoy":null,"gp_yoy":null,"dividend":null,"dividend_ttm":null,"dividend_yield":null,"payout_ratio":null,"ex_dividend_date":"18 May 22","div_history":[{"year":"2022","ex_date":"18 May 22","amount":7.5},{"year":"2021","ex_date":"10 May 21","amount":6.25},{"year":"2020","ex_date":"29 Jun 20","amount":6.25}],"ttm_revenue":311680892928,"ttm_gross":54615236608,"ttm_ebitda":36281860096,"ttm_net_income":8326346240,"ttm_op_income":null,"lq_cash":null,"lq_assets":null,"lq_tot_liab":null,"lq_wc":null,"lq_equity":null,"lq_lt_debt":null,"lq_st_debt":null,"lq_total_debt":null,"lq_net_debt":null,"ttm_ocf":-10759502848,"ttm_icf":null,"ttm_fincf":null,"ttm_capex":null,"ttm_fcf":-35255455744,"market_cap":306666668032,"enterprise_value":364850446336,"q_revenue":{},"q_net_income":{},"q_eps":{},"q_gross":{},"q_op_income":{},"q_assets":{},"q_equity":{},"q_debt":{},"q_cash":{},"q_ocf":{},"q_fcf":{},"a_revenue":{},"a_net_income":{},"hist_revenue":{},"hist_gross_profit":{},"hist_operating_income":{},"hist_net_income":{},"hist_total_assets":{},"hist_total_equity":{},"hist_total_debt":{},"price_perf":{},"hist_eps":{},"hist_fcf":{},"hist_bv":{},"hist_roe":{},"hist_dps":{"2020":6.25,"2021":6.25,"2022":7.5},"eps_cagr_3y":null,"eps_cagr_2y":null,"ddm_g_rate":9.5,"div_years":3,"sector_pe_median":11.9471,"sector_pb_median":1.3697,"sector_npm_median":0.0287,"sector_roe_median":0.0678,"sector_ev_ebitda_median":7.045,"sector_stock_count":37,"pe_vs_sector_pct":-40.8,"pb_vs_sector_pct":-59.4,"ps_vs_sector_pct":-44.3}