{"ticker": "WINR", "name": "PT Winner Nusantara Jaya Tbk", "sector": "Real Estate", "industry": "Real Estate - Development", "website": "https://winnernusantarajaya.id", "summary": "PT Winner Nusantara Jaya Tbk, together with its subsidiaries, operates as a property developer in Indonesia. The company operates through Residential House and Marketing Services segments. It is involved in the provision of real estate development services, residential house sales, and other services. The company also offers marketing services and management consulting services, as well as provide", "currency": "IDR", "updated": "2026-06-07 01:33", "last_price": 20.0, "prev_close": 22.0, "week52_high": 75.0, "week52_low": 20.0, "week52_change_pct": -4.0, "beta": 0.57, "avg_volume": 28285862, "shares": 5235316030, "float_shares": 2166007301, "float_pct": 41.37, "pe": 0.022030726, "pe_annualised": 0.022030726, "forward_pe": null, "earn_yield": 4539.12, "pb": 0.2884754, "ps": 1.9659975, "price_cf": 8.46, "price_fcf": 0.83, "ev_ebit": 12.971, "ev_ebitda": 12.971, "ev_revenue": 4.058, "peg": null, "eps": 907.823, "eps_fwd": null, "bv": 69.33, "rev_ps": 10.17, "cash_ps": null, "fcf_ps": 24.24, "current_ratio": 2.703, "quick_ratio": 0.147, "der": 25.079, "der_q": null, "lt_der_q": null, "tl_eq_q": null, "td_ta_q": null, "lev_q": null, "gpm": 0.45490003, "opm": 0.33612, "npm": 0.34235, "ebitda_margin": 0.31285, "roe": 0.04772, "roa": 0.0201, "rev_yoy": null, "ni_yoy": null, "gp_yoy": null, "dividend": null, "dividend_ttm": null, "dividend_yield": null, "payout_ratio": null, "ex_dividend_date": null, "div_history": [], "ttm_revenue": 53258629120, "ttm_gross": 24227325952, "ttm_ebitda": 16661705728, "ttm_net_income": 18233065472, "ttm_op_income": null, "lq_cash": null, "lq_assets": null, "lq_tot_liab": null, "lq_wc": null, "lq_equity": null, "lq_lt_debt": null, "lq_st_debt": null, "lq_total_debt": null, "lq_net_debt": null, "ttm_ocf": 12381291520, "ttm_icf": null, "ttm_fincf": null, "ttm_capex": null, "ttm_fcf": 126916370432, "market_cap": 104706326528, "enterprise_value": 216115068928, "q_revenue": {}, "q_net_income": {}, "q_eps": {}, "q_gross": {}, "q_op_income": {}, "q_assets": {}, "q_equity": {}, "q_debt": {}, "q_cash": {}, "q_ocf": {}, "q_fcf": {}, "a_revenue": {}, "a_net_income": {}, "hist_revenue": {}, "hist_gross_profit": {}, "hist_operating_income": {}, "hist_net_income": {}, "hist_total_assets": {}, "hist_total_equity": {}, "hist_total_debt": {}, "price_perf": {}, "hist_eps": {}, "hist_fcf": {}, "hist_bv": {}, "hist_roe": {}, "hist_dps": {}, "eps_cagr_3y": null, "eps_cagr_2y": null, "ddm_g_rate": null, "div_years": 0, "sector_pe_median": 14.9477, "sector_pb_median": 0.7579, "sector_npm_median": 0.1113, "sector_roe_median": 0.0237, "sector_ev_ebitda_median": 12.5185, "sector_stock_count": 89, "pe_vs_sector_pct": -99.9, "pb_vs_sector_pct": -61.9}