{"ticker": "ZBRA", "name": "PT Dosni Roha Indonesia Tbk", "sector": "Healthcare", "industry": "Medical Distribution", "website": "https://www.dnr.id", "summary": "PT Dosni Roha Indonesia Tbk, through its subsidiaries, engages in trading, export-import, logistic, and information technology (IT) businesses in Indonesia. It operates through Logistics, Technology and Information, Medical Equipment Trade, and Others segment. The company distributes health care and consumer goods; and provides freight forwarding and warehousing. It also offers transportation mana", "currency": "IDR", "updated": "2026-06-06 20:17", "last_price": 50.0, "prev_close": 50.0, "week52_high": 50.0, "week52_low": 50.0, "week52_change_pct": null, "beta": 0.04, "avg_volume": 0, "shares": 40082498, "float_shares": 913746437, "float_pct": 2279.66, "pe": null, "pe_annualised": null, "forward_pe": null, "earn_yield": null, "pb": 0.11446389, "ps": 0.028390668, "price_cf": 0.01, "price_fcf": 0.04, "ev_ebit": -15.082, "ev_ebitda": -15.082, "ev_revenue": 1.262, "peg": null, "eps": -50.87, "eps_fwd": null, "bv": 436.819, "rev_ps": 23471.96, "cash_ps": 217.83, "fcf_ps": 1245.76, "current_ratio": 1.351, "quick_ratio": 0.942, "der": 94.473, "der_q": null, "lt_der_q": null, "tl_eq_q": null, "td_ta_q": null, "lev_q": null, "gpm": 0.18712, "opm": -1.27346, "npm": -0.33574, "ebitda_margin": -0.083680004, "roe": -0.28336, "roa": -0.03156, "rev_yoy": null, "ni_yoy": null, "gp_yoy": null, "dividend": null, "dividend_ttm": null, "dividend_yield": null, "payout_ratio": 0.0, "ex_dividend_date": null, "div_history": [], "ttm_revenue": 940814893056, "ttm_gross": 176049258496, "ttm_ebitda": -78723145728, "ttm_net_income": -315868643328, "ttm_op_income": null, "lq_cash": 8731130254.0, "lq_assets": null, "lq_tot_liab": null, "lq_wc": null, "lq_equity": null, "lq_lt_debt": null, "lq_st_debt": null, "lq_total_debt": null, "lq_net_debt": null, "ttm_ocf": 336156131328, "ttm_icf": null, "ttm_fincf": null, "ttm_capex": null, "ttm_fcf": 49933103104, "market_cap": 26710364160, "enterprise_value": 1187278225408, "q_revenue": {}, "q_net_income": {}, "q_eps": {}, "q_gross": {}, "q_op_income": {}, "q_assets": {}, "q_equity": {}, "q_debt": {}, "q_cash": {"2024": {"Q3": 8731130254.0}}, "q_ocf": {}, "q_fcf": {}, "a_revenue": {"2023": 1724458039618.0, "2022": 2958367547579.0, "2021": 3497365178638.0}, "a_net_income": {"2023": -138619943547.0, "2022": -116617189131.0, "2021": 29029879858.0}, "hist_revenue": {"2023": 1724458039618.0, "2022": 2958367547579.0, "2021": 3497365178638.0}, "hist_gross_profit": {"2023": 356102355723.0, "2022": 350862487265.0, "2021": 486865892323.0}, "hist_operating_income": {"2023": -2674513483.0, "2022": -23340784575.0, "2021": 145890389874.0}, "hist_net_income": {"2023": -138619943547.0, "2022": -116617189131.0, "2021": 29029879858.0}, "hist_total_assets": {"2023": 3283128828277.0, "2022": 3156274366467.0, "2021": 3173972718466.0}, "hist_total_equity": {"2023": 1096723074780.0, "2022": 1248276101084.0, "2021": 1361906707107.0}, "hist_total_debt": {"2023": 871921742848.0, "2022": 1110821720261.0, "2021": 1142795069023.0}, "price_perf": {}}